puepy/__init__.py
puepy/application.py
puepy/core.py
puepy/exceptions.py
puepy/reactivity.py
puepy/router.py
puepy/runtime.py
puepy/storage.py
puepy/util.py
puepy/version.py
puepy-0.6.5.dist-info/LICENSE
puepy-0.6.5.dist-info/METADATA
puepy-0.6.5.dist-info/WHEEL
puepy-0.6.5.dist-info/RECORD
