Metadata-Version: 2.1
Name: puepy
Version: 0.6.5
Summary: Frontend Framework for PyScript
Home-page: https://puepy.dev/
License: Apache-2.0
Keywords: pyscript,webassembly,frontend,framework,reactive
Author: Ken Kinder
Author-email: ken+github@kkinder.com
Requires-Python: >=3.9,<4.0
Classifier: Development Status :: 3 - Alpha
Classifier: Environment :: Web Environment
Classifier: Environment :: WebAssembly
Classifier: Intended Audience :: Developers
Classifier: License :: OSI Approved :: Apache Software License
Classifier: Programming Language :: Python :: 3
Classifier: Programming Language :: Python :: 3.9
Classifier: Programming Language :: Python :: 3.10
Classifier: Programming Language :: Python :: 3.11
Classifier: Topic :: Software Development :: Libraries :: Application Frameworks
Project-URL: Documentation, https://docs.puepy.dev/
Project-URL: Repository, https://github.com/kkinder/puepy
